argvparser/__init__.py
argvparser/argvparser.py
argvparser-1.0.0.dist-info/METADATA
argvparser-1.0.0.dist-info/RECORD
argvparser-1.0.0.dist-info/WHEEL
argvparser-1.0.0.dist-info/top_level.txt
