Metadata-Version: 2.1
Name: argvparser
Version: 1.0.0
Summary: This module allows to format an argument vector in a structure easier to read and use for command line applications
Home-page: https://github.com/Arthuchaut/ArgvParser
Author: Arthuchaut
License: MIT
Platform: UNKNOWN
Classifier: Programming Language :: Python :: 3
Classifier: License :: OSI Approved :: MIT License
Classifier: Operating System :: OS Independent
